{ 
   "name":"Livro Power BI",
   "dataColors": ["#113F8C", "#01A4A4", "#00A1CB", "#61AE24", "#D0D102", "#32742C", "#D70060", "#E54028",    "#F18D05", "#616161"],
   "visualStyles":{ 
      "*":{ 
         "*":{ 
            "*":[ 
               { 
                  "fontSize":12,
                  "fontFamily":"Segoe UI"
               }
            ]
         }
      },
      "clusteredColumnChart":{ 
         "*":{ 
            "legend":[ 
               { 
                  "show":true,
                  "showTitle":true,
                  "fontSize":12,
                  "fontFamily":"Segoe (Bold)"
               }
            ],
            "valueAxis":[ 
               { 
                  "show":false
               }
            ],
            "labels":[ 
               { 
                  "show":true,
                  "fontFamily":"Segoe UI"
               }
            ]
         }
      }
   }
}
